itle-0.1.0-py3.7-nspkg.pth
itle/base.py
itle/ddk/__init__.py
itle/ddk/ddk_active_stat.py
itle/ddk/ddk_channel_type.py
itle/ddk/ddk_goods_sort_type.py
itle/ddk/ddk_one_yuan_param.py
itle/ddk/ddk_order_status.py
itle/ddk/ddk_pid_status.py
itle/ddk/ddk_red_packet_param.py
itle/ddk/ddk_resource_type.py
itle/ddk/rest/__init__.py
itle/ddk/rest/authority.py
itle/ddk/rest/cats.py
itle/ddk/rest/cms_prom_url.py
itle/ddk/rest/goods.py
itle/ddk/rest/order.py
itle/ddk/rest/pid.py
itle/ddk/rest/resource.py
itle/jd/__init__.py
itle-0.1.0.dist-info/LICENSE.txt
itle-0.1.0.dist-info/METADATA
itle-0.1.0.dist-info/WHEEL
itle-0.1.0.dist-info/namespace_packages.txt
itle-0.1.0.dist-info/top_level.txt
itle-0.1.0.dist-info/RECORD
